xtn/__init__.py
xtn/_xtn.py
xtn-0.4.0.dist-info/METADATA
xtn-0.4.0.dist-info/WHEEL
xtn-0.4.0.dist-info/RECORD
