Metadata-Version: 2.1
Name: xtn
Version: 0.4.0
Summary: A library for working with the xtn format
Home-page: https://github.com/koustubhmoharir/xtn
License: MIT
Author: Koustubh Moharir
Author-email: koustubhmoharir@gmail.com
Requires-Python: >=3.10,<4.0
Classifier: License :: OSI Approved :: MIT License
Classifier: Programming Language :: Python :: 3
Classifier: Programming Language :: Python :: 3.10
Classifier: Programming Language :: Python :: 3.11
